{
	"number-of-cards": 6,
	
	"assets":
	{
		"card-back": { "id": "back", "name": "back.png" },
		"cards": 
		[
			{ "id": "digit-0", "name": "digit-0.png" },
			{ "id": "digit-1", "name": "digit-1.png" },
			{ "id": "digit-2", "name": "digit-2.png" },
			{ "id": "digit-3", "name": "digit-3.png" },
			{ "id": "digit-4", "name": "digit-4.png" },
			{ "id": "digit-5", "name": "digit-5.png" },
			{ "id": "digit-6", "name": "digit-6.png" },
			{ "id": "digit-7", "name": "digit-7.png" },
			{ "id": "digit-8", "name": "digit-8.png" },
			{ "id": "digit-9", "name": "digit-9.png" }
		]
	}
}